icraft/__init__.py
icraft/adapt.cp38-win_amd64.pyd
icraft/buyi_codegen.cp38-win_amd64.pyd
icraft/buyi_codegen.pyi
icraft/buyibackend.cp38-win_amd64.pyd
icraft/buyibackend.pyi
icraft/codegen.cp38-win_amd64.pyd
icraft/host_backend.cp38-win_amd64.pyd
icraft/host_backend.pyi
icraft/parse.cp38-win_amd64.pyd
icraft/quantizer.cp38-win_amd64.pyd
icraft/xir.cp38-win_amd64.pyd
icraft/xir.pyi
icraft/xrt.cp38-win_amd64.pyd
icraft/xrt.pyi
icraft/zg330backend.cp38-win_amd64.pyd
icraft/zg330backend.pyi
icraft/zhuge_codegen.cp38-win_amd64.pyd
icraft-3.33.1.dist-info/METADATA
icraft-3.33.1.dist-info/WHEEL
icraft-3.33.1.dist-info/top_level.txt
icraft-3.33.1.dist-info/RECORD
