Metadata-Version: 2.1
Name: icraft
Version: 3.33.1
Summary: a whl for icraft
Home-page: UNKNOWN
Author: TangXiao
Author-email: tangxiao@fmsh.com.cn
Maintainer: WangYaMeng
Maintainer-email: wangyameng@fmsh.com.cn
License: GPL Licence
Platform: UNKNOWN
